equitrcoder/__init__.py
equitrcoder/agents/__init__.py
equitrcoder/agents/base_agent.py
equitrcoder/api/__init__.py
equitrcoder/api/model_api.py
equitrcoder/api/server.py
equitrcoder/cli/__init__.py
equitrcoder/cli/unified_main.py
equitrcoder/config/default.yaml
equitrcoder/config/profiles.yaml
equitrcoder/config/system_prompt.yaml
equitrcoder/core/__init__.py
equitrcoder/core/clean_agent.py
equitrcoder/core/clean_orchestrator.py
equitrcoder/core/config.py
equitrcoder/core/config_validator.py
equitrcoder/core/context_compressor.py
equitrcoder/core/context_manager.py
equitrcoder/core/dependency_injection.py
equitrcoder/core/document_generators.py
equitrcoder/core/documentation.py
equitrcoder/core/file_cache.py
equitrcoder/core/global_message_pool.py
equitrcoder/core/interfaces.py
equitrcoder/core/model_manager.py
equitrcoder/core/performance_analyzer.py
equitrcoder/core/performance_monitor.py
equitrcoder/core/planning.py
equitrcoder/core/profile_manager.py
equitrcoder/core/session.py
equitrcoder/core/standardized_error_handler.py
equitrcoder/core/string_optimizer.py
equitrcoder/core/task.py
equitrcoder/core/todo_parser.py
equitrcoder/core/unified_config.py
equitrcoder/core/validation_engine.py
equitrcoder/profiles/__init__.py
equitrcoder/profiles/audio_engineer.yaml
equitrcoder/profiles/backend_dev.yaml
equitrcoder/profiles/data_engineer.yaml
equitrcoder/profiles/devops.yaml
equitrcoder/profiles/experiment_runner.yaml
equitrcoder/profiles/frontend_dev.yaml
equitrcoder/profiles/game_dev.yaml
equitrcoder/profiles/level_designer.yaml
equitrcoder/profiles/ml_researcher.yaml
equitrcoder/profiles/qa_engineer.yaml
equitrcoder/programmatic/__init__.py
equitrcoder/programmatic/interface.py
equitrcoder/providers/__init__.py
equitrcoder/providers/function_calling_discovery.py
equitrcoder/providers/litellm.py
equitrcoder/providers/model_discovery.py
equitrcoder/providers/openrouter.py
equitrcoder/repository/__init__.py
equitrcoder/repository/analyzer.py
equitrcoder-2.3.0.dist-info/licenses/LICENSE
equitrcoder-2.3.0.dist-info/METADATA
equitrcoder-2.3.0.dist-info/WHEEL
equitrcoder-2.3.0.dist-info/entry_points.txt
equitrcoder-2.3.0.dist-info/top_level.txt
equitrcoder-2.3.0.dist-info/RECORD
