Metadata-Version: 2.4
Name: equitrcoder
Version: 2.3.0
Summary: Modular AI coding assistant supporting single and multi-agent workflows
Home-page: https://github.com/tanushv/equitrcoder
Author: EQUITR
Author-email: tanushvanarase@equitr.com
Project-URL: Bug Reports, https://github.com/equitr/equitrcoder/issues
Project-URL: Source, https://github.com/equitr/equitrcoder
Project-URL: Documentation, https://equitrcoder.readthedocs.io/
Keywords: ai coding assistant agent multi-agent llm automation
Classifier: Development Status :: 4 - Beta
Classifier: Intended Audience :: Developers
Classifier: License :: OSI Approved :: MIT License
Classifier: Operating System :: OS Independent
Classifier: Programming Language :: Python :: 3
Classifier: Programming Language :: Python :: 3.10
Classifier: Programming Language :: Python :: 3.11
Classifier: Programming Language :: Python :: 3.12
Classifier: Topic :: Software Development :: Code Generators
Classifier: Topic :: Software Development :: Libraries :: Python Modules
Classifier: Topic :: Scientific/Engineering :: Artificial Intelligence
Requires-Python: >=3.10
License-File: LICENSE
Provides-Extra: api
Requires-Dist: fastapi>=0.104.0; extra == "api"
Requires-Dist: uvicorn>=0.24.0; extra == "api"
Provides-Extra: tui
Requires-Dist: textual>=0.45.0; extra == "tui"
Requires-Dist: rich>=13.0.0; extra == "tui"
Provides-Extra: dev
Requires-Dist: pytest>=7.4.0; extra == "dev"
Requires-Dist: pytest-asyncio>=0.21.0; extra == "dev"
Requires-Dist: black>=23.0.0; extra == "dev"
Requires-Dist: flake8>=6.0.0; extra == "dev"
Requires-Dist: mypy>=1.6.0; extra == "dev"
Requires-Dist: isort>=5.12.0; extra == "dev"
Provides-Extra: all
Requires-Dist: fastapi>=0.104.0; extra == "all"
Requires-Dist: uvicorn>=0.24.0; extra == "all"
Requires-Dist: textual>=0.45.0; extra == "all"
Requires-Dist: rich>=13.0.0; extra == "all"
Dynamic: author
Dynamic: author-email
Dynamic: classifier
Dynamic: description
Dynamic: description-content-type
Dynamic: home-page
Dynamic: keywords
Dynamic: license-file
Dynamic: project-url
Dynamic: provides-extra
Dynamic: requires-python
Dynamic: summary
